[
  {
    "id": 1,
    "title": "Spaghetti Carbonara",
    "summary": "A classic Italian pasta dish with eggs, cheese, bacon, and black pepper.",
    "image": "https://images.pexels.com/photos/1437267/pexels-photo-1437267.jpeg"
  },
  {
    "id": 2,
    "title": "Chicken Tikka in Smooth Buttery Tomato Cream",
    "summary": "A flavorful Indian dish with grilled chicken in a rich tomato cream sauce.",
    "image":  "https://images.pexels.com/photos/1640777/pexels-photo-1640777.jpeg"
  
  }
  
    
  
]
